{
  "columns": 246,
  "rows": 38,
  "ticks": [
    {
      "label": 2005,
      "major": true,
      "x": 0
    },
    {
      "label": 2006,
      "major": false,
      "x": 12
    },
    {
      "label": 2007,
      "major": false,
      "x": 24
    },
    {
      "label": 2008,
      "major": false,
      "x": 36
    },
    {
      "label": 2009,
      "major": false,
      "x": 48
    },
    {
      "label": 2010,
      "major": true,
      "x": 60
    },
    {
      "label": 2011,
      "major": false,
      "x": 72
    },
    {
      "label": 2012,
      "major": false,
      "x": 84
    },
    {
      "label": 2013,
      "major": false,
      "x": 96
    },
    {
      "label": 2014,
      "major": false,
      "x": 108
    },
    {
      "label": 2015,
      "major": true,
      "x": 120
    },
    {
      "label": 2016,
      "major": false,
      "x": 132
    },
    {
      "label": 2017,
      "major": false,
      "x": 144
    },
    {
      "label": 2018,
      "major": false,
      "x": 156
    },
    {
      "label": 2019,
      "major": false,
      "x": 168
    },
    {
      "label": 2020,
      "major": true,
      "x": 180
    },
    {
      "label": 2021,
      "major": false,
      "x": 192
    },
    {
      "label": 2022,
      "major": false,
      "x": 204
    },
    {
      "label": 2023,
      "major": false,
      "x": 216
    },
    {
      "label": 2024,
      "major": false,
      "x": 228
    },
    {
      "label": 2025,
      "major": true,
      "x": 240
    }
  ],
  "data": [
    {
      "x": 6,
      "y": 18
    },
    {
      "x": 7,
      "y": 18
    },
    {
      "x": 10,
      "y": 18
    },
    {
      "x": 11,
      "y": 18
    },
    {
      "x": 14,
      "y": 18
    },
    {
      "x": 15,
      "y": 18
    },
    {
      "x": 16,
      "y": 18
    },
    {
      "x": 16,
      "y": 19
    },
    {
      "x": 19,
      "y": 16
    },
    {
      "x": 19,
      "y": 17
    },
    {
      "x": 19,
      "y": 18
    },
    {
      "x": 19,
      "y": 19
    },
    {
      "x": 19,
      "y": 20
    },
    {
      "x": 20,
      "y": 17
    },
    {
      "x": 20,
      "y": 18
    },
    {
      "x": 20,
      "y": 19
    },
    {
      "x": 21,
      "y": 18
    },
    {
      "x": 22,
      "y": 18
    },
    {
      "x": 23,
      "y": 18
    },
    {
      "x": 26,
      "y": 18
    },
    {
      "x": 27,
      "y": 18
    },
    {
      "x": 27,
      "y": 19
    },
    {
      "x": 28,
      "y": 18
    },
    {
      "x": 29,
      "y": 18
    },
    {
      "x": 30,
      "y": 18
    },
    {
      "x": 30,
      "y": 19
    },
    {
      "x": 31,
      "y": 18
    },
    {
      "x": 33,
      "y": 18
    },
    {
      "x": 33,
      "y": 19
    },
    {
      "x": 37,
      "y": 18
    },
    {
      "x": 39,
      "y": 18
    },
    {
      "x": 40,
      "y": 18
    },
    {
      "x": 41,
      "y": 18
    },
    {
      "x": 42,
      "y": 18
    },
    {
      "x": 45,
      "y": 18
    },
    {
      "x": 46,
      "y": 17
    },
    {
      "x": 46,
      "y": 18
    },
    {
      "x": 46,
      "y": 19
    },
    {
      "x": 47,
      "y": 17
    },
    {
      "x": 47,
      "y": 18
    },
    {
      "x": 47,
      "y": 19
    },
    {
      "x": 48,
      "y": 11
    },
    {
      "x": 48,
      "y": 12
    },
    {
      "x": 48,
      "y": 13
    },
    {
      "x": 48,
      "y": 14
    },
    {
      "x": 48,
      "y": 15
    },
    {
      "x": 48,
      "y": 16
    },
    {
      "x": 48,
      "y": 17
    },
    {
      "x": 48,
      "y": 18
    },
    {
      "x": 48,
      "y": 19
    },
    {
      "x": 48,
      "y": 20
    },
    {
      "x": 48,
      "y": 21
    },
    {
      "x": 48,
      "y": 22
    },
    {
      "x": 48,
      "y": 23
    },
    {
      "x": 48,
      "y": 24
    },
    {
      "x": 48,
      "y": 25
    },
    {
      "x": 48,
      "y": 26
    },
    {
      "x": 49,
      "y": 15
    },
    {
      "x": 49,
      "y": 16
    },
    {
      "x": 49,
      "y": 17
    },
    {
      "x": 49,
      "y": 18
    },
    {
      "x": 49,
      "y": 19
    },
    {
      "x": 49,
      "y": 20
    },
    {
      "x": 49,
      "y": 21
    },
    {
      "x": 49,
      "y": 22
    },
    {
      "x": 50,
      "y": 16
    },
    {
      "x": 50,
      "y": 17
    },
    {
      "x": 50,
      "y": 18
    },
    {
      "x": 50,
      "y": 19
    },
    {
      "x": 50,
      "y": 20
    },
    {
      "x": 50,
      "y": 21
    },
    {
      "x": 51,
      "y": 17
    },
    {
      "x": 51,
      "y": 18
    },
    {
      "x": 51,
      "y": 19
    },
    {
      "x": 51,
      "y": 20
    },
    {
      "x": 53,
      "y": 17
    },
    {
      "x": 53,
      "y": 18
    },
    {
      "x": 53,
      "y": 19
    },
    {
      "x": 53,
      "y": 20
    },
    {
      "x": 54,
      "y": 18
    },
    {
      "x": 54,
      "y": 19
    },
    {
      "x": 55,
      "y": 18
    },
    {
      "x": 55,
      "y": 19
    },
    {
      "x": 56,
      "y": 15
    },
    {
      "x": 56,
      "y": 16
    },
    {
      "x": 56,
      "y": 17
    },
    {
      "x": 56,
      "y": 18
    },
    {
      "x": 56,
      "y": 19
    },
    {
      "x": 56,
      "y": 20
    },
    {
      "x": 56,
      "y": 21
    },
    {
      "x": 58,
      "y": 17
    },
    {
      "x": 58,
      "y": 18
    },
    {
      "x": 58,
      "y": 19
    },
    {
      "x": 59,
      "y": 17
    },
    {
      "x": 59,
      "y": 18
    },
    {
      "x": 59,
      "y": 19
    },
    {
      "x": 60,
      "y": 16
    },
    {
      "x": 60,
      "y": 17
    },
    {
      "x": 60,
      "y": 18
    },
    {
      "x": 60,
      "y": 19
    },
    {
      "x": 60,
      "y": 20
    },
    {
      "x": 61,
      "y": 17
    },
    {
      "x": 61,
      "y": 18
    },
    {
      "x": 61,
      "y": 19
    },
    {
      "x": 62,
      "y": 18
    },
    {
      "x": 62,
      "y": 19
    },
    {
      "x": 63,
      "y": 17
    },
    {
      "x": 63,
      "y": 18
    },
    {
      "x": 63,
      "y": 19
    },
    {
      "x": 63,
      "y": 20
    },
    {
      "x": 64,
      "y": 15
    },
    {
      "x": 64,
      "y": 16
    },
    {
      "x": 64,
      "y": 17
    },
    {
      "x": 64,
      "y": 18
    },
    {
      "x": 64,
      "y": 19
    },
    {
      "x": 64,
      "y": 20
    },
    {
      "x": 64,
      "y": 21
    },
    {
      "x": 65,
      "y": 9
    },
    {
      "x": 65,
      "y": 10
    },
    {
      "x": 65,
      "y": 11
    },
    {
      "x": 65,
      "y": 12
    },
    {
      "x": 65,
      "y": 13
    },
    {
      "x": 65,
      "y": 14
    },
    {
      "x": 65,
      "y": 15
    },
    {
      "x": 65,
      "y": 16
    },
    {
      "x": 65,
      "y": 17
    },
    {
      "x": 65,
      "y": 18
    },
    {
      "x": 65,
      "y": 19
    },
    {
      "x": 65,
      "y": 20
    },
    {
      "x": 65,
      "y": 21
    },
    {
      "x": 65,
      "y": 22
    },
    {
      "x": 65,
      "y": 23
    },
    {
      "x": 65,
      "y": 24
    },
    {
      "x": 65,
      "y": 25
    },
    {
      "x": 65,
      "y": 26
    },
    {
      "x": 65,
      "y": 27
    },
    {
      "x": 65,
      "y": 28
    },
    {
      "x": 66,
      "y": 14
    },
    {
      "x": 66,
      "y": 15
    },
    {
      "x": 66,
      "y": 16
    },
    {
      "x": 66,
      "y": 17
    },
    {
      "x": 66,
      "y": 18
    },
    {
      "x": 66,
      "y": 19
    },
    {
      "x": 66,
      "y": 20
    },
    {
      "x": 66,
      "y": 21
    },
    {
      "x": 66,
      "y": 22
    },
    {
      "x": 66,
      "y": 23
    },
    {
      "x": 67,
      "y": 17
    },
    {
      "x": 67,
      "y": 18
    },
    {
      "x": 67,
      "y": 19
    },
    {
      "x": 68,
      "y": 18
    },
    {
      "x": 69,
      "y": 17
    },
    {
      "x": 69,
      "y": 18
    },
    {
      "x": 69,
      "y": 19
    },
    {
      "x": 70,
      "y": 15
    },
    {
      "x": 70,
      "y": 16
    },
    {
      "x": 70,
      "y": 17
    },
    {
      "x": 70,
      "y": 18
    },
    {
      "x": 70,
      "y": 19
    },
    {
      "x": 70,
      "y": 20
    },
    {
      "x": 70,
      "y": 21
    },
    {
      "x": 71,
      "y": 18
    },
    {
      "x": 71,
      "y": 19
    },
    {
      "x": 72,
      "y": 17
    },
    {
      "x": 72,
      "y": 18
    },
    {
      "x": 72,
      "y": 19
    },
    {
      "x": 72,
      "y": 20
    },
    {
      "x": 73,
      "y": 17
    },
    {
      "x": 73,
      "y": 18
    },
    {
      "x": 73,
      "y": 19
    },
    {
      "x": 74,
      "y": 13
    },
    {
      "x": 74,
      "y": 14
    },
    {
      "x": 74,
      "y": 15
    },
    {
      "x": 74,
      "y": 16
    },
    {
      "x": 74,
      "y": 17
    },
    {
      "x": 74,
      "y": 18
    },
    {
      "x": 74,
      "y": 19
    },
    {
      "x": 74,
      "y": 20
    },
    {
      "x": 74,
      "y": 21
    },
    {
      "x": 74,
      "y": 22
    },
    {
      "x": 74,
      "y": 23
    },
    {
      "x": 75,
      "y": 17
    },
    {
      "x": 75,
      "y": 18
    },
    {
      "x": 75,
      "y": 19
    },
    {
      "x": 75,
      "y": 20
    },
    {
      "x": 76,
      "y": 15
    },
    {
      "x": 76,
      "y": 16
    },
    {
      "x": 76,
      "y": 17
    },
    {
      "x": 76,
      "y": 18
    },
    {
      "x": 76,
      "y": 19
    },
    {
      "x": 76,
      "y": 20
    },
    {
      "x": 76,
      "y": 21
    },
    {
      "x": 77,
      "y": 18
    },
    {
      "x": 77,
      "y": 19
    },
    {
      "x": 78,
      "y": 17
    },
    {
      "x": 78,
      "y": 18
    },
    {
      "x": 78,
      "y": 19
    },
    {
      "x": 79,
      "y": 17
    },
    {
      "x": 79,
      "y": 18
    },
    {
      "x": 79,
      "y": 19
    },
    {
      "x": 80,
      "y": 17
    },
    {
      "x": 80,
      "y": 18
    },
    {
      "x": 80,
      "y": 19
    },
    {
      "x": 80,
      "y": 20
    },
    {
      "x": 81,
      "y": 13
    },
    {
      "x": 81,
      "y": 14
    },
    {
      "x": 81,
      "y": 15
    },
    {
      "x": 81,
      "y": 16
    },
    {
      "x": 81,
      "y": 17
    },
    {
      "x": 81,
      "y": 18
    },
    {
      "x": 81,
      "y": 19
    },
    {
      "x": 81,
      "y": 20
    },
    {
      "x": 81,
      "y": 21
    },
    {
      "x": 81,
      "y": 22
    },
    {
      "x": 81,
      "y": 23
    },
    {
      "x": 83,
      "y": 18
    },
    {
      "x": 83,
      "y": 19
    },
    {
      "x": 84,
      "y": 18
    },
    {
      "x": 84,
      "y": 19
    },
    {
      "x": 85,
      "y": 15
    },
    {
      "x": 85,
      "y": 16
    },
    {
      "x": 85,
      "y": 17
    },
    {
      "x": 85,
      "y": 18
    },
    {
      "x": 85,
      "y": 19
    },
    {
      "x": 85,
      "y": 20
    },
    {
      "x": 85,
      "y": 21
    },
    {
      "x": 86,
      "y": 15
    },
    {
      "x": 86,
      "y": 16
    },
    {
      "x": 86,
      "y": 17
    },
    {
      "x": 86,
      "y": 18
    },
    {
      "x": 86,
      "y": 19
    },
    {
      "x": 86,
      "y": 20
    },
    {
      "x": 86,
      "y": 21
    },
    {
      "x": 86,
      "y": 22
    },
    {
      "x": 87,
      "y": 15
    },
    {
      "x": 87,
      "y": 16
    },
    {
      "x": 87,
      "y": 17
    },
    {
      "x": 87,
      "y": 18
    },
    {
      "x": 87,
      "y": 19
    },
    {
      "x": 87,
      "y": 20
    },
    {
      "x": 87,
      "y": 21
    },
    {
      "x": 87,
      "y": 22
    },
    {
      "x": 88,
      "y": 16
    },
    {
      "x": 88,
      "y": 17
    },
    {
      "x": 88,
      "y": 18
    },
    {
      "x": 88,
      "y": 19
    },
    {
      "x": 88,
      "y": 20
    },
    {
      "x": 88,
      "y": 21
    },
    {
      "x": 89,
      "y": 16
    },
    {
      "x": 89,
      "y": 17
    },
    {
      "x": 89,
      "y": 18
    },
    {
      "x": 89,
      "y": 19
    },
    {
      "x": 89,
      "y": 20
    },
    {
      "x": 90,
      "y": 17
    },
    {
      "x": 90,
      "y": 18
    },
    {
      "x": 90,
      "y": 19
    },
    {
      "x": 91,
      "y": 17
    },
    {
      "x": 91,
      "y": 18
    },
    {
      "x": 91,
      "y": 19
    },
    {
      "x": 92,
      "y": 15
    },
    {
      "x": 92,
      "y": 16
    },
    {
      "x": 92,
      "y": 17
    },
    {
      "x": 92,
      "y": 18
    },
    {
      "x": 92,
      "y": 19
    },
    {
      "x": 92,
      "y": 20
    },
    {
      "x": 92,
      "y": 21
    },
    {
      "x": 93,
      "y": 16
    },
    {
      "x": 93,
      "y": 17
    },
    {
      "x": 93,
      "y": 18
    },
    {
      "x": 93,
      "y": 19
    },
    {
      "x": 93,
      "y": 20
    },
    {
      "x": 94,
      "y": 16
    },
    {
      "x": 94,
      "y": 17
    },
    {
      "x": 94,
      "y": 18
    },
    {
      "x": 94,
      "y": 19
    },
    {
      "x": 94,
      "y": 20
    },
    {
      "x": 95,
      "y": 14
    },
    {
      "x": 95,
      "y": 15
    },
    {
      "x": 95,
      "y": 16
    },
    {
      "x": 95,
      "y": 17
    },
    {
      "x": 95,
      "y": 18
    },
    {
      "x": 95,
      "y": 19
    },
    {
      "x": 95,
      "y": 20
    },
    {
      "x": 95,
      "y": 21
    },
    {
      "x": 95,
      "y": 22
    },
    {
      "x": 95,
      "y": 23
    },
    {
      "x": 96,
      "y": 15
    },
    {
      "x": 96,
      "y": 16
    },
    {
      "x": 96,
      "y": 17
    },
    {
      "x": 96,
      "y": 18
    },
    {
      "x": 96,
      "y": 19
    },
    {
      "x": 96,
      "y": 20
    },
    {
      "x": 96,
      "y": 21
    },
    {
      "x": 96,
      "y": 22
    },
    {
      "x": 97,
      "y": 16
    },
    {
      "x": 97,
      "y": 17
    },
    {
      "x": 97,
      "y": 18
    },
    {
      "x": 97,
      "y": 19
    },
    {
      "x": 97,
      "y": 20
    },
    {
      "x": 98,
      "y": 16
    },
    {
      "x": 98,
      "y": 17
    },
    {
      "x": 98,
      "y": 18
    },
    {
      "x": 98,
      "y": 19
    },
    {
      "x": 98,
      "y": 20
    },
    {
      "x": 99,
      "y": 15
    },
    {
      "x": 99,
      "y": 16
    },
    {
      "x": 99,
      "y": 17
    },
    {
      "x": 99,
      "y": 18
    },
    {
      "x": 99,
      "y": 19
    },
    {
      "x": 99,
      "y": 20
    },
    {
      "x": 99,
      "y": 21
    },
    {
      "x": 100,
      "y": 17
    },
    {
      "x": 100,
      "y": 18
    },
    {
      "x": 100,
      "y": 19
    },
    {
      "x": 100,
      "y": 20
    },
    {
      "x": 101,
      "y": 18
    },
    {
      "x": 101,
      "y": 19
    },
    {
      "x": 102,
      "y": 17
    },
    {
      "x": 102,
      "y": 18
    },
    {
      "x": 102,
      "y": 19
    },
    {
      "x": 102,
      "y": 20
    },
    {
      "x": 103,
      "y": 17
    },
    {
      "x": 103,
      "y": 18
    },
    {
      "x": 103,
      "y": 19
    },
    {
      "x": 104,
      "y": 17
    },
    {
      "x": 104,
      "y": 18
    },
    {
      "x": 104,
      "y": 19
    },
    {
      "x": 105,
      "y": 17
    },
    {
      "x": 105,
      "y": 18
    },
    {
      "x": 105,
      "y": 19
    },
    {
      "x": 105,
      "y": 20
    },
    {
      "x": 106,
      "y": 16
    },
    {
      "x": 106,
      "y": 17
    },
    {
      "x": 106,
      "y": 18
    },
    {
      "x": 106,
      "y": 19
    },
    {
      "x": 106,
      "y": 20
    },
    {
      "x": 107,
      "y": 15
    },
    {
      "x": 107,
      "y": 16
    },
    {
      "x": 107,
      "y": 17
    },
    {
      "x": 107,
      "y": 18
    },
    {
      "x": 107,
      "y": 19
    },
    {
      "x": 107,
      "y": 20
    },
    {
      "x": 107,
      "y": 21
    },
    {
      "x": 108,
      "y": 14
    },
    {
      "x": 108,
      "y": 15
    },
    {
      "x": 108,
      "y": 16
    },
    {
      "x": 108,
      "y": 17
    },
    {
      "x": 108,
      "y": 18
    },
    {
      "x": 108,
      "y": 19
    },
    {
      "x": 108,
      "y": 20
    },
    {
      "x": 108,
      "y": 21
    },
    {
      "x": 108,
      "y": 22
    },
    {
      "x": 109,
      "y": 17
    },
    {
      "x": 109,
      "y": 18
    },
    {
      "x": 109,
      "y": 19
    },
    {
      "x": 110,
      "y": 14
    },
    {
      "x": 110,
      "y": 15
    },
    {
      "x": 110,
      "y": 16
    },
    {
      "x": 110,
      "y": 17
    },
    {
      "x": 110,
      "y": 18
    },
    {
      "x": 110,
      "y": 19
    },
    {
      "x": 110,
      "y": 20
    },
    {
      "x": 110,
      "y": 21
    },
    {
      "x": 110,
      "y": 22
    },
    {
      "x": 110,
      "y": 23
    },
    {
      "x": 111,
      "y": 16
    },
    {
      "x": 111,
      "y": 17
    },
    {
      "x": 111,
      "y": 18
    },
    {
      "x": 111,
      "y": 19
    },
    {
      "x": 111,
      "y": 20
    },
    {
      "x": 111,
      "y": 21
    },
    {
      "x": 112,
      "y": 14
    },
    {
      "x": 112,
      "y": 15
    },
    {
      "x": 112,
      "y": 16
    },
    {
      "x": 112,
      "y": 17
    },
    {
      "x": 112,
      "y": 18
    },
    {
      "x": 112,
      "y": 19
    },
    {
      "x": 112,
      "y": 20
    },
    {
      "x": 112,
      "y": 21
    },
    {
      "x": 112,
      "y": 22
    },
    {
      "x": 112,
      "y": 23
    },
    {
      "x": 113,
      "y": 17
    },
    {
      "x": 113,
      "y": 18
    },
    {
      "x": 113,
      "y": 19
    },
    {
      "x": 114,
      "y": 8
    },
    {
      "x": 114,
      "y": 9
    },
    {
      "x": 114,
      "y": 10
    },
    {
      "x": 114,
      "y": 11
    },
    {
      "x": 114,
      "y": 12
    },
    {
      "x": 114,
      "y": 13
    },
    {
      "x": 114,
      "y": 14
    },
    {
      "x": 114,
      "y": 15
    },
    {
      "x": 114,
      "y": 16
    },
    {
      "x": 114,
      "y": 17
    },
    {
      "x": 114,
      "y": 18
    },
    {
      "x": 114,
      "y": 19
    },
    {
      "x": 114,
      "y": 20
    },
    {
      "x": 114,
      "y": 21
    },
    {
      "x": 114,
      "y": 22
    },
    {
      "x": 114,
      "y": 23
    },
    {
      "x": 114,
      "y": 24
    },
    {
      "x": 114,
      "y": 25
    },
    {
      "x": 114,
      "y": 26
    },
    {
      "x": 114,
      "y": 27
    },
    {
      "x": 114,
      "y": 28
    },
    {
      "x": 115,
      "y": 12
    },
    {
      "x": 115,
      "y": 13
    },
    {
      "x": 115,
      "y": 14
    },
    {
      "x": 115,
      "y": 15
    },
    {
      "x": 115,
      "y": 16
    },
    {
      "x": 115,
      "y": 17
    },
    {
      "x": 115,
      "y": 18
    },
    {
      "x": 115,
      "y": 19
    },
    {
      "x": 115,
      "y": 20
    },
    {
      "x": 115,
      "y": 21
    },
    {
      "x": 115,
      "y": 22
    },
    {
      "x": 115,
      "y": 23
    },
    {
      "x": 115,
      "y": 24
    },
    {
      "x": 116,
      "y": 17
    },
    {
      "x": 116,
      "y": 18
    },
    {
      "x": 116,
      "y": 19
    },
    {
      "x": 116,
      "y": 20
    },
    {
      "x": 117,
      "y": 16
    },
    {
      "x": 117,
      "y": 17
    },
    {
      "x": 117,
      "y": 18
    },
    {
      "x": 117,
      "y": 19
    },
    {
      "x": 117,
      "y": 20
    },
    {
      "x": 117,
      "y": 21
    },
    {
      "x": 118,
      "y": 15
    },
    {
      "x": 118,
      "y": 16
    },
    {
      "x": 118,
      "y": 17
    },
    {
      "x": 118,
      "y": 18
    },
    {
      "x": 118,
      "y": 19
    },
    {
      "x": 118,
      "y": 20
    },
    {
      "x": 118,
      "y": 21
    },
    {
      "x": 119,
      "y": 15
    },
    {
      "x": 119,
      "y": 16
    },
    {
      "x": 119,
      "y": 17
    },
    {
      "x": 119,
      "y": 18
    },
    {
      "x": 119,
      "y": 19
    },
    {
      "x": 119,
      "y": 20
    },
    {
      "x": 119,
      "y": 21
    },
    {
      "x": 120,
      "y": 17
    },
    {
      "x": 120,
      "y": 18
    },
    {
      "x": 120,
      "y": 19
    },
    {
      "x": 120,
      "y": 20
    },
    {
      "x": 121,
      "y": 17
    },
    {
      "x": 121,
      "y": 18
    },
    {
      "x": 121,
      "y": 19
    },
    {
      "x": 121,
      "y": 20
    },
    {
      "x": 122,
      "y": 16
    },
    {
      "x": 122,
      "y": 17
    },
    {
      "x": 122,
      "y": 18
    },
    {
      "x": 122,
      "y": 19
    },
    {
      "x": 122,
      "y": 20
    },
    {
      "x": 122,
      "y": 21
    },
    {
      "x": 123,
      "y": 16
    },
    {
      "x": 123,
      "y": 17
    },
    {
      "x": 123,
      "y": 18
    },
    {
      "x": 123,
      "y": 19
    },
    {
      "x": 123,
      "y": 20
    },
    {
      "x": 123,
      "y": 21
    },
    {
      "x": 124,
      "y": 13
    },
    {
      "x": 124,
      "y": 14
    },
    {
      "x": 124,
      "y": 15
    },
    {
      "x": 124,
      "y": 16
    },
    {
      "x": 124,
      "y": 17
    },
    {
      "x": 124,
      "y": 18
    },
    {
      "x": 124,
      "y": 19
    },
    {
      "x": 124,
      "y": 20
    },
    {
      "x": 124,
      "y": 21
    },
    {
      "x": 124,
      "y": 22
    },
    {
      "x": 124,
      "y": 23
    },
    {
      "x": 124,
      "y": 24
    },
    {
      "x": 125,
      "y": 16
    },
    {
      "x": 125,
      "y": 17
    },
    {
      "x": 125,
      "y": 18
    },
    {
      "x": 125,
      "y": 19
    },
    {
      "x": 125,
      "y": 20
    },
    {
      "x": 125,
      "y": 21
    },
    {
      "x": 126,
      "y": 17
    },
    {
      "x": 126,
      "y": 18
    },
    {
      "x": 126,
      "y": 19
    },
    {
      "x": 126,
      "y": 20
    },
    {
      "x": 127,
      "y": 17
    },
    {
      "x": 127,
      "y": 18
    },
    {
      "x": 127,
      "y": 19
    },
    {
      "x": 128,
      "y": 16
    },
    {
      "x": 128,
      "y": 17
    },
    {
      "x": 128,
      "y": 18
    },
    {
      "x": 128,
      "y": 19
    },
    {
      "x": 128,
      "y": 20
    },
    {
      "x": 129,
      "y": 14
    },
    {
      "x": 129,
      "y": 15
    },
    {
      "x": 129,
      "y": 16
    },
    {
      "x": 129,
      "y": 17
    },
    {
      "x": 129,
      "y": 18
    },
    {
      "x": 129,
      "y": 19
    },
    {
      "x": 129,
      "y": 20
    },
    {
      "x": 129,
      "y": 21
    },
    {
      "x": 129,
      "y": 22
    },
    {
      "x": 130,
      "y": 16
    },
    {
      "x": 130,
      "y": 17
    },
    {
      "x": 130,
      "y": 18
    },
    {
      "x": 130,
      "y": 19
    },
    {
      "x": 130,
      "y": 20
    },
    {
      "x": 130,
      "y": 21
    },
    {
      "x": 131,
      "y": 17
    },
    {
      "x": 131,
      "y": 18
    },
    {
      "x": 131,
      "y": 19
    },
    {
      "x": 131,
      "y": 20
    },
    {
      "x": 132,
      "y": 16
    },
    {
      "x": 132,
      "y": 17
    },
    {
      "x": 132,
      "y": 18
    },
    {
      "x": 132,
      "y": 19
    },
    {
      "x": 132,
      "y": 20
    },
    {
      "x": 132,
      "y": 21
    },
    {
      "x": 133,
      "y": 17
    },
    {
      "x": 133,
      "y": 18
    },
    {
      "x": 133,
      "y": 19
    },
    {
      "x": 134,
      "y": 15
    },
    {
      "x": 134,
      "y": 16
    },
    {
      "x": 134,
      "y": 17
    },
    {
      "x": 134,
      "y": 18
    },
    {
      "x": 134,
      "y": 19
    },
    {
      "x": 134,
      "y": 20
    },
    {
      "x": 134,
      "y": 21
    },
    {
      "x": 134,
      "y": 22
    },
    {
      "x": 135,
      "y": 15
    },
    {
      "x": 135,
      "y": 16
    },
    {
      "x": 135,
      "y": 17
    },
    {
      "x": 135,
      "y": 18
    },
    {
      "x": 135,
      "y": 19
    },
    {
      "x": 135,
      "y": 20
    },
    {
      "x": 135,
      "y": 21
    },
    {
      "x": 135,
      "y": 22
    },
    {
      "x": 136,
      "y": 14
    },
    {
      "x": 136,
      "y": 15
    },
    {
      "x": 136,
      "y": 16
    },
    {
      "x": 136,
      "y": 17
    },
    {
      "x": 136,
      "y": 18
    },
    {
      "x": 136,
      "y": 19
    },
    {
      "x": 136,
      "y": 20
    },
    {
      "x": 136,
      "y": 21
    },
    {
      "x": 136,
      "y": 22
    },
    {
      "x": 136,
      "y": 23
    },
    {
      "x": 137,
      "y": 15
    },
    {
      "x": 137,
      "y": 16
    },
    {
      "x": 137,
      "y": 17
    },
    {
      "x": 137,
      "y": 18
    },
    {
      "x": 137,
      "y": 19
    },
    {
      "x": 137,
      "y": 20
    },
    {
      "x": 137,
      "y": 21
    },
    {
      "x": 138,
      "y": 14
    },
    {
      "x": 138,
      "y": 15
    },
    {
      "x": 138,
      "y": 16
    },
    {
      "x": 138,
      "y": 17
    },
    {
      "x": 138,
      "y": 18
    },
    {
      "x": 138,
      "y": 19
    },
    {
      "x": 138,
      "y": 20
    },
    {
      "x": 138,
      "y": 21
    },
    {
      "x": 138,
      "y": 22
    },
    {
      "x": 138,
      "y": 23
    },
    {
      "x": 139,
      "y": 17
    },
    {
      "x": 139,
      "y": 18
    },
    {
      "x": 139,
      "y": 19
    },
    {
      "x": 139,
      "y": 20
    },
    {
      "x": 140,
      "y": 18
    },
    {
      "x": 140,
      "y": 19
    },
    {
      "x": 141,
      "y": 16
    },
    {
      "x": 141,
      "y": 17
    },
    {
      "x": 141,
      "y": 18
    },
    {
      "x": 141,
      "y": 19
    },
    {
      "x": 141,
      "y": 20
    },
    {
      "x": 142,
      "y": 16
    },
    {
      "x": 142,
      "y": 17
    },
    {
      "x": 142,
      "y": 18
    },
    {
      "x": 142,
      "y": 19
    },
    {
      "x": 142,
      "y": 20
    },
    {
      "x": 142,
      "y": 21
    },
    {
      "x": 143,
      "y": 13
    },
    {
      "x": 143,
      "y": 14
    },
    {
      "x": 143,
      "y": 15
    },
    {
      "x": 143,
      "y": 16
    },
    {
      "x": 143,
      "y": 17
    },
    {
      "x": 143,
      "y": 18
    },
    {
      "x": 143,
      "y": 19
    },
    {
      "x": 143,
      "y": 20
    },
    {
      "x": 143,
      "y": 21
    },
    {
      "x": 143,
      "y": 22
    },
    {
      "x": 143,
      "y": 23
    },
    {
      "x": 143,
      "y": 24
    },
    {
      "x": 144,
      "y": 18
    },
    {
      "x": 145,
      "y": 18
    },
    {
      "x": 146,
      "y": 17
    },
    {
      "x": 146,
      "y": 18
    },
    {
      "x": 146,
      "y": 19
    },
    {
      "x": 147,
      "y": 16
    },
    {
      "x": 147,
      "y": 17
    },
    {
      "x": 147,
      "y": 18
    },
    {
      "x": 147,
      "y": 19
    },
    {
      "x": 147,
      "y": 20
    },
    {
      "x": 148,
      "y": 18
    },
    {
      "x": 148,
      "y": 19
    },
    {
      "x": 149,
      "y": 15
    },
    {
      "x": 149,
      "y": 16
    },
    {
      "x": 149,
      "y": 17
    },
    {
      "x": 149,
      "y": 18
    },
    {
      "x": 149,
      "y": 19
    },
    {
      "x": 149,
      "y": 20
    },
    {
      "x": 149,
      "y": 21
    },
    {
      "x": 150,
      "y": 16
    },
    {
      "x": 150,
      "y": 17
    },
    {
      "x": 150,
      "y": 18
    },
    {
      "x": 150,
      "y": 19
    },
    {
      "x": 150,
      "y": 20
    },
    {
      "x": 150,
      "y": 21
    },
    {
      "x": 151,
      "y": 16
    },
    {
      "x": 151,
      "y": 17
    },
    {
      "x": 151,
      "y": 18
    },
    {
      "x": 151,
      "y": 19
    },
    {
      "x": 151,
      "y": 20
    },
    {
      "x": 152,
      "y": 17
    },
    {
      "x": 152,
      "y": 18
    },
    {
      "x": 152,
      "y": 19
    },
    {
      "x": 153,
      "y": 16
    },
    {
      "x": 153,
      "y": 17
    },
    {
      "x": 153,
      "y": 18
    },
    {
      "x": 153,
      "y": 19
    },
    {
      "x": 153,
      "y": 20
    },
    {
      "x": 154,
      "y": 16
    },
    {
      "x": 154,
      "y": 17
    },
    {
      "x": 154,
      "y": 18
    },
    {
      "x": 154,
      "y": 19
    },
    {
      "x": 154,
      "y": 20
    },
    {
      "x": 154,
      "y": 21
    },
    {
      "x": 155,
      "y": 17
    },
    {
      "x": 155,
      "y": 18
    },
    {
      "x": 155,
      "y": 19
    },
    {
      "x": 155,
      "y": 20
    },
    {
      "x": 156,
      "y": 17
    },
    {
      "x": 156,
      "y": 18
    },
    {
      "x": 156,
      "y": 19
    },
    {
      "x": 156,
      "y": 20
    },
    {
      "x": 157,
      "y": 16
    },
    {
      "x": 157,
      "y": 17
    },
    {
      "x": 157,
      "y": 18
    },
    {
      "x": 157,
      "y": 19
    },
    {
      "x": 157,
      "y": 20
    },
    {
      "x": 157,
      "y": 21
    },
    {
      "x": 158,
      "y": 18
    },
    {
      "x": 158,
      "y": 19
    },
    {
      "x": 159,
      "y": 11
    },
    {
      "x": 159,
      "y": 12
    },
    {
      "x": 159,
      "y": 13
    },
    {
      "x": 159,
      "y": 14
    },
    {
      "x": 159,
      "y": 15
    },
    {
      "x": 159,
      "y": 16
    },
    {
      "x": 159,
      "y": 17
    },
    {
      "x": 159,
      "y": 18
    },
    {
      "x": 159,
      "y": 19
    },
    {
      "x": 159,
      "y": 20
    },
    {
      "x": 159,
      "y": 21
    },
    {
      "x": 159,
      "y": 22
    },
    {
      "x": 159,
      "y": 23
    },
    {
      "x": 159,
      "y": 24
    },
    {
      "x": 159,
      "y": 25
    },
    {
      "x": 159,
      "y": 26
    },
    {
      "x": 160,
      "y": 6
    },
    {
      "x": 160,
      "y": 7
    },
    {
      "x": 160,
      "y": 8
    },
    {
      "x": 160,
      "y": 9
    },
    {
      "x": 160,
      "y": 10
    },
    {
      "x": 160,
      "y": 11
    },
    {
      "x": 160,
      "y": 12
    },
    {
      "x": 160,
      "y": 13
    },
    {
      "x": 160,
      "y": 14
    },
    {
      "x": 160,
      "y": 15
    },
    {
      "x": 160,
      "y": 16
    },
    {
      "x": 160,
      "y": 17
    },
    {
      "x": 160,
      "y": 18
    },
    {
      "x": 160,
      "y": 19
    },
    {
      "x": 160,
      "y": 20
    },
    {
      "x": 160,
      "y": 21
    },
    {
      "x": 160,
      "y": 22
    },
    {
      "x": 160,
      "y": 23
    },
    {
      "x": 160,
      "y": 24
    },
    {
      "x": 160,
      "y": 25
    },
    {
      "x": 160,
      "y": 26
    },
    {
      "x": 160,
      "y": 27
    },
    {
      "x": 160,
      "y": 28
    },
    {
      "x": 160,
      "y": 29
    },
    {
      "x": 160,
      "y": 30
    },
    {
      "x": 160,
      "y": 31
    },
    {
      "x": 161,
      "y": 15
    },
    {
      "x": 161,
      "y": 16
    },
    {
      "x": 161,
      "y": 17
    },
    {
      "x": 161,
      "y": 18
    },
    {
      "x": 161,
      "y": 19
    },
    {
      "x": 161,
      "y": 20
    },
    {
      "x": 161,
      "y": 21
    },
    {
      "x": 161,
      "y": 22
    },
    {
      "x": 162,
      "y": 12
    },
    {
      "x": 162,
      "y": 13
    },
    {
      "x": 162,
      "y": 14
    },
    {
      "x": 162,
      "y": 15
    },
    {
      "x": 162,
      "y": 16
    },
    {
      "x": 162,
      "y": 17
    },
    {
      "x": 162,
      "y": 18
    },
    {
      "x": 162,
      "y": 19
    },
    {
      "x": 162,
      "y": 20
    },
    {
      "x": 162,
      "y": 21
    },
    {
      "x": 162,
      "y": 22
    },
    {
      "x": 162,
      "y": 23
    },
    {
      "x": 162,
      "y": 24
    },
    {
      "x": 162,
      "y": 25
    },
    {
      "x": 163,
      "y": 16
    },
    {
      "x": 163,
      "y": 17
    },
    {
      "x": 163,
      "y": 18
    },
    {
      "x": 163,
      "y": 19
    },
    {
      "x": 163,
      "y": 20
    },
    {
      "x": 164,
      "y": 15
    },
    {
      "x": 164,
      "y": 16
    },
    {
      "x": 164,
      "y": 17
    },
    {
      "x": 164,
      "y": 18
    },
    {
      "x": 164,
      "y": 19
    },
    {
      "x": 164,
      "y": 20
    },
    {
      "x": 164,
      "y": 21
    },
    {
      "x": 164,
      "y": 22
    },
    {
      "x": 165,
      "y": 18
    },
    {
      "x": 166,
      "y": 15
    },
    {
      "x": 166,
      "y": 16
    },
    {
      "x": 166,
      "y": 17
    },
    {
      "x": 166,
      "y": 18
    },
    {
      "x": 166,
      "y": 19
    },
    {
      "x": 166,
      "y": 20
    },
    {
      "x": 166,
      "y": 21
    },
    {
      "x": 166,
      "y": 22
    },
    {
      "x": 167,
      "y": 16
    },
    {
      "x": 167,
      "y": 17
    },
    {
      "x": 167,
      "y": 18
    },
    {
      "x": 167,
      "y": 19
    },
    {
      "x": 167,
      "y": 20
    },
    {
      "x": 168,
      "y": 17
    },
    {
      "x": 168,
      "y": 18
    },
    {
      "x": 168,
      "y": 19
    },
    {
      "x": 169,
      "y": 17
    },
    {
      "x": 169,
      "y": 18
    },
    {
      "x": 169,
      "y": 19
    },
    {
      "x": 170,
      "y": 15
    },
    {
      "x": 170,
      "y": 16
    },
    {
      "x": 170,
      "y": 17
    },
    {
      "x": 170,
      "y": 18
    },
    {
      "x": 170,
      "y": 19
    },
    {
      "x": 170,
      "y": 20
    },
    {
      "x": 170,
      "y": 21
    },
    {
      "x": 170,
      "y": 22
    },
    {
      "x": 171,
      "y": 15
    },
    {
      "x": 171,
      "y": 16
    },
    {
      "x": 171,
      "y": 17
    },
    {
      "x": 171,
      "y": 18
    },
    {
      "x": 171,
      "y": 19
    },
    {
      "x": 171,
      "y": 20
    },
    {
      "x": 171,
      "y": 21
    },
    {
      "x": 172,
      "y": 16
    },
    {
      "x": 172,
      "y": 17
    },
    {
      "x": 172,
      "y": 18
    },
    {
      "x": 172,
      "y": 19
    },
    {
      "x": 172,
      "y": 20
    },
    {
      "x": 172,
      "y": 21
    },
    {
      "x": 173,
      "y": 15
    },
    {
      "x": 173,
      "y": 16
    },
    {
      "x": 173,
      "y": 17
    },
    {
      "x": 173,
      "y": 18
    },
    {
      "x": 173,
      "y": 19
    },
    {
      "x": 173,
      "y": 20
    },
    {
      "x": 173,
      "y": 21
    },
    {
      "x": 173,
      "y": 22
    },
    {
      "x": 174,
      "y": 16
    },
    {
      "x": 174,
      "y": 17
    },
    {
      "x": 174,
      "y": 18
    },
    {
      "x": 174,
      "y": 19
    },
    {
      "x": 174,
      "y": 20
    },
    {
      "x": 174,
      "y": 21
    },
    {
      "x": 175,
      "y": 17
    },
    {
      "x": 175,
      "y": 18
    },
    {
      "x": 175,
      "y": 19
    },
    {
      "x": 175,
      "y": 20
    },
    {
      "x": 176,
      "y": 15
    },
    {
      "x": 176,
      "y": 16
    },
    {
      "x": 176,
      "y": 17
    },
    {
      "x": 176,
      "y": 18
    },
    {
      "x": 176,
      "y": 19
    },
    {
      "x": 176,
      "y": 20
    },
    {
      "x": 176,
      "y": 21
    },
    {
      "x": 177,
      "y": 16
    },
    {
      "x": 177,
      "y": 17
    },
    {
      "x": 177,
      "y": 18
    },
    {
      "x": 177,
      "y": 19
    },
    {
      "x": 177,
      "y": 20
    },
    {
      "x": 177,
      "y": 21
    },
    {
      "x": 178,
      "y": 16
    },
    {
      "x": 178,
      "y": 17
    },
    {
      "x": 178,
      "y": 18
    },
    {
      "x": 178,
      "y": 19
    },
    {
      "x": 178,
      "y": 20
    },
    {
      "x": 179,
      "y": 18
    },
    {
      "x": 179,
      "y": 19
    },
    {
      "x": 180,
      "y": 18
    },
    {
      "x": 181,
      "y": 16
    },
    {
      "x": 181,
      "y": 17
    },
    {
      "x": 181,
      "y": 18
    },
    {
      "x": 181,
      "y": 19
    },
    {
      "x": 181,
      "y": 20
    },
    {
      "x": 181,
      "y": 21
    },
    {
      "x": 182,
      "y": 17
    },
    {
      "x": 182,
      "y": 18
    },
    {
      "x": 182,
      "y": 19
    },
    {
      "x": 182,
      "y": 20
    },
    {
      "x": 183,
      "y": 17
    },
    {
      "x": 183,
      "y": 18
    },
    {
      "x": 183,
      "y": 19
    },
    {
      "x": 184,
      "y": 16
    },
    {
      "x": 184,
      "y": 17
    },
    {
      "x": 184,
      "y": 18
    },
    {
      "x": 184,
      "y": 19
    },
    {
      "x": 184,
      "y": 20
    },
    {
      "x": 185,
      "y": 16
    },
    {
      "x": 185,
      "y": 17
    },
    {
      "x": 185,
      "y": 18
    },
    {
      "x": 185,
      "y": 19
    },
    {
      "x": 185,
      "y": 20
    },
    {
      "x": 186,
      "y": 16
    },
    {
      "x": 186,
      "y": 17
    },
    {
      "x": 186,
      "y": 18
    },
    {
      "x": 186,
      "y": 19
    },
    {
      "x": 186,
      "y": 20
    },
    {
      "x": 187,
      "y": 17
    },
    {
      "x": 187,
      "y": 18
    },
    {
      "x": 187,
      "y": 19
    },
    {
      "x": 187,
      "y": 20
    },
    {
      "x": 188,
      "y": 14
    },
    {
      "x": 188,
      "y": 15
    },
    {
      "x": 188,
      "y": 16
    },
    {
      "x": 188,
      "y": 17
    },
    {
      "x": 188,
      "y": 18
    },
    {
      "x": 188,
      "y": 19
    },
    {
      "x": 188,
      "y": 20
    },
    {
      "x": 188,
      "y": 21
    },
    {
      "x": 188,
      "y": 22
    },
    {
      "x": 189,
      "y": 17
    },
    {
      "x": 189,
      "y": 18
    },
    {
      "x": 189,
      "y": 19
    },
    {
      "x": 189,
      "y": 20
    },
    {
      "x": 190,
      "y": 15
    },
    {
      "x": 190,
      "y": 16
    },
    {
      "x": 190,
      "y": 17
    },
    {
      "x": 190,
      "y": 18
    },
    {
      "x": 190,
      "y": 19
    },
    {
      "x": 190,
      "y": 20
    },
    {
      "x": 190,
      "y": 21
    },
    {
      "x": 190,
      "y": 22
    },
    {
      "x": 191,
      "y": 17
    },
    {
      "x": 191,
      "y": 18
    },
    {
      "x": 191,
      "y": 19
    },
    {
      "x": 191,
      "y": 20
    },
    {
      "x": 192,
      "y": 17
    },
    {
      "x": 192,
      "y": 18
    },
    {
      "x": 192,
      "y": 19
    },
    {
      "x": 193,
      "y": 18
    },
    {
      "x": 193,
      "y": 19
    },
    {
      "x": 194,
      "y": 17
    },
    {
      "x": 194,
      "y": 18
    },
    {
      "x": 194,
      "y": 19
    },
    {
      "x": 195,
      "y": 17
    },
    {
      "x": 195,
      "y": 18
    },
    {
      "x": 195,
      "y": 19
    },
    {
      "x": 195,
      "y": 20
    },
    {
      "x": 196,
      "y": 17
    },
    {
      "x": 196,
      "y": 18
    },
    {
      "x": 196,
      "y": 19
    },
    {
      "x": 196,
      "y": 20
    },
    {
      "x": 197,
      "y": 12
    },
    {
      "x": 197,
      "y": 13
    },
    {
      "x": 197,
      "y": 14
    },
    {
      "x": 197,
      "y": 15
    },
    {
      "x": 197,
      "y": 16
    },
    {
      "x": 197,
      "y": 17
    },
    {
      "x": 197,
      "y": 18
    },
    {
      "x": 197,
      "y": 19
    },
    {
      "x": 197,
      "y": 20
    },
    {
      "x": 197,
      "y": 21
    },
    {
      "x": 197,
      "y": 22
    },
    {
      "x": 197,
      "y": 23
    },
    {
      "x": 197,
      "y": 24
    },
    {
      "x": 197,
      "y": 25
    },
    {
      "x": 198,
      "y": 15
    },
    {
      "x": 198,
      "y": 16
    },
    {
      "x": 198,
      "y": 17
    },
    {
      "x": 198,
      "y": 18
    },
    {
      "x": 198,
      "y": 19
    },
    {
      "x": 198,
      "y": 20
    },
    {
      "x": 198,
      "y": 21
    },
    {
      "x": 200,
      "y": 18
    },
    {
      "x": 201,
      "y": 17
    },
    {
      "x": 201,
      "y": 18
    },
    {
      "x": 201,
      "y": 19
    },
    {
      "x": 202,
      "y": 15
    },
    {
      "x": 202,
      "y": 16
    },
    {
      "x": 202,
      "y": 17
    },
    {
      "x": 202,
      "y": 18
    },
    {
      "x": 202,
      "y": 19
    },
    {
      "x": 202,
      "y": 20
    },
    {
      "x": 202,
      "y": 21
    },
    {
      "x": 202,
      "y": 22
    },
    {
      "x": 203,
      "y": 18
    },
    {
      "x": 203,
      "y": 19
    },
    {
      "x": 204,
      "y": 17
    },
    {
      "x": 204,
      "y": 18
    },
    {
      "x": 204,
      "y": 19
    },
    {
      "x": 205,
      "y": 18
    },
    {
      "x": 205,
      "y": 19
    },
    {
      "x": 206,
      "y": 17
    },
    {
      "x": 206,
      "y": 18
    },
    {
      "x": 206,
      "y": 19
    },
    {
      "x": 206,
      "y": 20
    },
    {
      "x": 207,
      "y": 18
    },
    {
      "x": 207,
      "y": 19
    },
    {
      "x": 208,
      "y": 17
    },
    {
      "x": 208,
      "y": 18
    },
    {
      "x": 208,
      "y": 19
    },
    {
      "x": 208,
      "y": 20
    },
    {
      "x": 209,
      "y": 15
    },
    {
      "x": 209,
      "y": 16
    },
    {
      "x": 209,
      "y": 17
    },
    {
      "x": 209,
      "y": 18
    },
    {
      "x": 209,
      "y": 19
    },
    {
      "x": 209,
      "y": 20
    },
    {
      "x": 209,
      "y": 21
    },
    {
      "x": 209,
      "y": 22
    },
    {
      "x": 210,
      "y": 18
    },
    {
      "x": 210,
      "y": 19
    },
    {
      "x": 211,
      "y": 17
    },
    {
      "x": 211,
      "y": 18
    },
    {
      "x": 211,
      "y": 19
    },
    {
      "x": 212,
      "y": 17
    },
    {
      "x": 212,
      "y": 18
    },
    {
      "x": 212,
      "y": 19
    },
    {
      "x": 212,
      "y": 20
    },
    {
      "x": 213,
      "y": 17
    },
    {
      "x": 213,
      "y": 18
    },
    {
      "x": 213,
      "y": 19
    },
    {
      "x": 213,
      "y": 20
    },
    {
      "x": 214,
      "y": 17
    },
    {
      "x": 214,
      "y": 18
    },
    {
      "x": 214,
      "y": 19
    },
    {
      "x": 215,
      "y": 18
    },
    {
      "x": 216,
      "y": 18
    },
    {
      "x": 217,
      "y": 17
    },
    {
      "x": 217,
      "y": 18
    },
    {
      "x": 217,
      "y": 19
    },
    {
      "x": 218,
      "y": 17
    },
    {
      "x": 218,
      "y": 18
    },
    {
      "x": 218,
      "y": 19
    },
    {
      "x": 219,
      "y": 15
    },
    {
      "x": 219,
      "y": 16
    },
    {
      "x": 219,
      "y": 17
    },
    {
      "x": 219,
      "y": 18
    },
    {
      "x": 219,
      "y": 19
    },
    {
      "x": 219,
      "y": 20
    },
    {
      "x": 219,
      "y": 21
    },
    {
      "x": 219,
      "y": 22
    },
    {
      "x": 220,
      "y": 17
    },
    {
      "x": 220,
      "y": 18
    },
    {
      "x": 220,
      "y": 19
    },
    {
      "x": 220,
      "y": 20
    },
    {
      "x": 221,
      "y": 18
    },
    {
      "x": 221,
      "y": 19
    },
    {
      "x": 222,
      "y": 17
    },
    {
      "x": 222,
      "y": 18
    },
    {
      "x": 222,
      "y": 19
    },
    {
      "x": 223,
      "y": 17
    },
    {
      "x": 223,
      "y": 18
    },
    {
      "x": 223,
      "y": 19
    },
    {
      "x": 224,
      "y": 18
    },
    {
      "x": 225,
      "y": 16
    },
    {
      "x": 225,
      "y": 17
    },
    {
      "x": 225,
      "y": 18
    },
    {
      "x": 225,
      "y": 19
    },
    {
      "x": 225,
      "y": 20
    },
    {
      "x": 226,
      "y": 14
    },
    {
      "x": 226,
      "y": 15
    },
    {
      "x": 226,
      "y": 16
    },
    {
      "x": 226,
      "y": 17
    },
    {
      "x": 226,
      "y": 18
    },
    {
      "x": 226,
      "y": 19
    },
    {
      "x": 226,
      "y": 20
    },
    {
      "x": 226,
      "y": 21
    },
    {
      "x": 226,
      "y": 22
    },
    {
      "x": 227,
      "y": 17
    },
    {
      "x": 227,
      "y": 18
    },
    {
      "x": 227,
      "y": 19
    },
    {
      "x": 227,
      "y": 20
    },
    {
      "x": 228,
      "y": 12
    },
    {
      "x": 228,
      "y": 13
    },
    {
      "x": 228,
      "y": 14
    },
    {
      "x": 228,
      "y": 15
    },
    {
      "x": 228,
      "y": 16
    },
    {
      "x": 228,
      "y": 17
    },
    {
      "x": 228,
      "y": 18
    },
    {
      "x": 228,
      "y": 19
    },
    {
      "x": 228,
      "y": 20
    },
    {
      "x": 228,
      "y": 21
    },
    {
      "x": 228,
      "y": 22
    },
    {
      "x": 228,
      "y": 23
    },
    {
      "x": 228,
      "y": 24
    },
    {
      "x": 229,
      "y": 8
    },
    {
      "x": 229,
      "y": 9
    },
    {
      "x": 229,
      "y": 10
    },
    {
      "x": 229,
      "y": 11
    },
    {
      "x": 229,
      "y": 12
    },
    {
      "x": 229,
      "y": 13
    },
    {
      "x": 229,
      "y": 14
    },
    {
      "x": 229,
      "y": 15
    },
    {
      "x": 229,
      "y": 16
    },
    {
      "x": 229,
      "y": 17
    },
    {
      "x": 229,
      "y": 18
    },
    {
      "x": 229,
      "y": 19
    },
    {
      "x": 229,
      "y": 20
    },
    {
      "x": 229,
      "y": 21
    },
    {
      "x": 229,
      "y": 22
    },
    {
      "x": 229,
      "y": 23
    },
    {
      "x": 229,
      "y": 24
    },
    {
      "x": 229,
      "y": 25
    },
    {
      "x": 229,
      "y": 26
    },
    {
      "x": 229,
      "y": 27
    },
    {
      "x": 229,
      "y": 28
    },
    {
      "x": 229,
      "y": 29
    },
    {
      "x": 230,
      "y": 8
    },
    {
      "x": 230,
      "y": 9
    },
    {
      "x": 230,
      "y": 10
    },
    {
      "x": 230,
      "y": 11
    },
    {
      "x": 230,
      "y": 12
    },
    {
      "x": 230,
      "y": 13
    },
    {
      "x": 230,
      "y": 14
    },
    {
      "x": 230,
      "y": 15
    },
    {
      "x": 230,
      "y": 16
    },
    {
      "x": 230,
      "y": 17
    },
    {
      "x": 230,
      "y": 18
    },
    {
      "x": 230,
      "y": 19
    },
    {
      "x": 230,
      "y": 20
    },
    {
      "x": 230,
      "y": 21
    },
    {
      "x": 230,
      "y": 22
    },
    {
      "x": 230,
      "y": 23
    },
    {
      "x": 230,
      "y": 24
    },
    {
      "x": 230,
      "y": 25
    },
    {
      "x": 230,
      "y": 26
    },
    {
      "x": 230,
      "y": 27
    },
    {
      "x": 230,
      "y": 28
    },
    {
      "x": 231,
      "y": 10
    },
    {
      "x": 231,
      "y": 11
    },
    {
      "x": 231,
      "y": 12
    },
    {
      "x": 231,
      "y": 13
    },
    {
      "x": 231,
      "y": 14
    },
    {
      "x": 231,
      "y": 15
    },
    {
      "x": 231,
      "y": 16
    },
    {
      "x": 231,
      "y": 17
    },
    {
      "x": 231,
      "y": 18
    },
    {
      "x": 231,
      "y": 19
    },
    {
      "x": 231,
      "y": 20
    },
    {
      "x": 231,
      "y": 21
    },
    {
      "x": 231,
      "y": 22
    },
    {
      "x": 231,
      "y": 23
    },
    {
      "x": 231,
      "y": 24
    },
    {
      "x": 231,
      "y": 25
    },
    {
      "x": 231,
      "y": 26
    },
    {
      "x": 232,
      "y": 0
    },
    {
      "x": 232,
      "y": 1
    },
    {
      "x": 232,
      "y": 2
    },
    {
      "x": 232,
      "y": 3
    },
    {
      "x": 232,
      "y": 4
    },
    {
      "x": 232,
      "y": 5
    },
    {
      "x": 232,
      "y": 6
    },
    {
      "x": 232,
      "y": 7
    },
    {
      "x": 232,
      "y": 8
    },
    {
      "x": 232,
      "y": 9
    },
    {
      "x": 232,
      "y": 10
    },
    {
      "x": 232,
      "y": 11
    },
    {
      "x": 232,
      "y": 12
    },
    {
      "x": 232,
      "y": 13
    },
    {
      "x": 232,
      "y": 14
    },
    {
      "x": 232,
      "y": 15
    },
    {
      "x": 232,
      "y": 16
    },
    {
      "x": 232,
      "y": 17
    },
    {
      "x": 232,
      "y": 18
    },
    {
      "x": 232,
      "y": 19
    },
    {
      "x": 232,
      "y": 20
    },
    {
      "x": 232,
      "y": 21
    },
    {
      "x": 232,
      "y": 22
    },
    {
      "x": 232,
      "y": 23
    },
    {
      "x": 232,
      "y": 24
    },
    {
      "x": 232,
      "y": 25
    },
    {
      "x": 232,
      "y": 26
    },
    {
      "x": 232,
      "y": 27
    },
    {
      "x": 232,
      "y": 28
    },
    {
      "x": 232,
      "y": 29
    },
    {
      "x": 232,
      "y": 30
    },
    {
      "x": 232,
      "y": 31
    },
    {
      "x": 232,
      "y": 32
    },
    {
      "x": 232,
      "y": 33
    },
    {
      "x": 232,
      "y": 34
    },
    {
      "x": 232,
      "y": 35
    },
    {
      "x": 232,
      "y": 36
    },
    {
      "x": 232,
      "y": 37
    },
    {
      "x": 233,
      "y": 3
    },
    {
      "x": 233,
      "y": 4
    },
    {
      "x": 233,
      "y": 5
    },
    {
      "x": 233,
      "y": 6
    },
    {
      "x": 233,
      "y": 7
    },
    {
      "x": 233,
      "y": 8
    },
    {
      "x": 233,
      "y": 9
    },
    {
      "x": 233,
      "y": 10
    },
    {
      "x": 233,
      "y": 11
    },
    {
      "x": 233,
      "y": 12
    },
    {
      "x": 233,
      "y": 13
    },
    {
      "x": 233,
      "y": 14
    },
    {
      "x": 233,
      "y": 15
    },
    {
      "x": 233,
      "y": 16
    },
    {
      "x": 233,
      "y": 17
    },
    {
      "x": 233,
      "y": 18
    },
    {
      "x": 233,
      "y": 19
    },
    {
      "x": 233,
      "y": 20
    },
    {
      "x": 233,
      "y": 21
    },
    {
      "x": 233,
      "y": 22
    },
    {
      "x": 233,
      "y": 23
    },
    {
      "x": 233,
      "y": 24
    },
    {
      "x": 233,
      "y": 25
    },
    {
      "x": 233,
      "y": 26
    },
    {
      "x": 233,
      "y": 27
    },
    {
      "x": 233,
      "y": 28
    },
    {
      "x": 233,
      "y": 29
    },
    {
      "x": 233,
      "y": 30
    },
    {
      "x": 233,
      "y": 31
    },
    {
      "x": 233,
      "y": 32
    },
    {
      "x": 233,
      "y": 33
    },
    {
      "x": 234,
      "y": 5
    },
    {
      "x": 234,
      "y": 6
    },
    {
      "x": 234,
      "y": 7
    },
    {
      "x": 234,
      "y": 8
    },
    {
      "x": 234,
      "y": 9
    },
    {
      "x": 234,
      "y": 10
    },
    {
      "x": 234,
      "y": 11
    },
    {
      "x": 234,
      "y": 12
    },
    {
      "x": 234,
      "y": 13
    },
    {
      "x": 234,
      "y": 14
    },
    {
      "x": 234,
      "y": 15
    },
    {
      "x": 234,
      "y": 16
    },
    {
      "x": 234,
      "y": 17
    },
    {
      "x": 234,
      "y": 18
    },
    {
      "x": 234,
      "y": 19
    },
    {
      "x": 234,
      "y": 20
    },
    {
      "x": 234,
      "y": 21
    },
    {
      "x": 234,
      "y": 22
    },
    {
      "x": 234,
      "y": 23
    },
    {
      "x": 234,
      "y": 24
    },
    {
      "x": 234,
      "y": 25
    },
    {
      "x": 234,
      "y": 26
    },
    {
      "x": 234,
      "y": 27
    },
    {
      "x": 234,
      "y": 28
    },
    {
      "x": 234,
      "y": 29
    },
    {
      "x": 234,
      "y": 30
    },
    {
      "x": 234,
      "y": 31
    },
    {
      "x": 235,
      "y": 9
    },
    {
      "x": 235,
      "y": 10
    },
    {
      "x": 235,
      "y": 11
    },
    {
      "x": 235,
      "y": 12
    },
    {
      "x": 235,
      "y": 13
    },
    {
      "x": 235,
      "y": 14
    },
    {
      "x": 235,
      "y": 15
    },
    {
      "x": 235,
      "y": 16
    },
    {
      "x": 235,
      "y": 17
    },
    {
      "x": 235,
      "y": 18
    },
    {
      "x": 235,
      "y": 19
    },
    {
      "x": 235,
      "y": 20
    },
    {
      "x": 235,
      "y": 21
    },
    {
      "x": 235,
      "y": 22
    },
    {
      "x": 235,
      "y": 23
    },
    {
      "x": 235,
      "y": 24
    },
    {
      "x": 235,
      "y": 25
    },
    {
      "x": 235,
      "y": 26
    },
    {
      "x": 235,
      "y": 27
    },
    {
      "x": 235,
      "y": 28
    },
    {
      "x": 236,
      "y": 4
    },
    {
      "x": 236,
      "y": 5
    },
    {
      "x": 236,
      "y": 6
    },
    {
      "x": 236,
      "y": 7
    },
    {
      "x": 236,
      "y": 8
    },
    {
      "x": 236,
      "y": 9
    },
    {
      "x": 236,
      "y": 10
    },
    {
      "x": 236,
      "y": 11
    },
    {
      "x": 236,
      "y": 12
    },
    {
      "x": 236,
      "y": 13
    },
    {
      "x": 236,
      "y": 14
    },
    {
      "x": 236,
      "y": 15
    },
    {
      "x": 236,
      "y": 16
    },
    {
      "x": 236,
      "y": 17
    },
    {
      "x": 236,
      "y": 18
    },
    {
      "x": 236,
      "y": 19
    },
    {
      "x": 236,
      "y": 20
    },
    {
      "x": 236,
      "y": 21
    },
    {
      "x": 236,
      "y": 22
    },
    {
      "x": 236,
      "y": 23
    },
    {
      "x": 236,
      "y": 24
    },
    {
      "x": 236,
      "y": 25
    },
    {
      "x": 236,
      "y": 26
    },
    {
      "x": 236,
      "y": 27
    },
    {
      "x": 236,
      "y": 28
    },
    {
      "x": 236,
      "y": 29
    },
    {
      "x": 236,
      "y": 30
    },
    {
      "x": 236,
      "y": 31
    },
    {
      "x": 236,
      "y": 32
    },
    {
      "x": 236,
      "y": 33
    },
    {
      "x": 237,
      "y": 0
    },
    {
      "x": 237,
      "y": 1
    },
    {
      "x": 237,
      "y": 2
    },
    {
      "x": 237,
      "y": 3
    },
    {
      "x": 237,
      "y": 4
    },
    {
      "x": 237,
      "y": 5
    },
    {
      "x": 237,
      "y": 6
    },
    {
      "x": 237,
      "y": 7
    },
    {
      "x": 237,
      "y": 8
    },
    {
      "x": 237,
      "y": 9
    },
    {
      "x": 237,
      "y": 10
    },
    {
      "x": 237,
      "y": 11
    },
    {
      "x": 237,
      "y": 12
    },
    {
      "x": 237,
      "y": 13
    },
    {
      "x": 237,
      "y": 14
    },
    {
      "x": 237,
      "y": 15
    },
    {
      "x": 237,
      "y": 16
    },
    {
      "x": 237,
      "y": 17
    },
    {
      "x": 237,
      "y": 18
    },
    {
      "x": 237,
      "y": 19
    },
    {
      "x": 237,
      "y": 20
    },
    {
      "x": 237,
      "y": 21
    },
    {
      "x": 237,
      "y": 22
    },
    {
      "x": 237,
      "y": 23
    },
    {
      "x": 237,
      "y": 24
    },
    {
      "x": 237,
      "y": 25
    },
    {
      "x": 237,
      "y": 26
    },
    {
      "x": 237,
      "y": 27
    },
    {
      "x": 237,
      "y": 28
    },
    {
      "x": 237,
      "y": 29
    },
    {
      "x": 237,
      "y": 30
    },
    {
      "x": 237,
      "y": 31
    },
    {
      "x": 237,
      "y": 32
    },
    {
      "x": 237,
      "y": 33
    },
    {
      "x": 237,
      "y": 34
    },
    {
      "x": 237,
      "y": 35
    },
    {
      "x": 237,
      "y": 36
    },
    {
      "x": 238,
      "y": 4
    },
    {
      "x": 238,
      "y": 5
    },
    {
      "x": 238,
      "y": 6
    },
    {
      "x": 238,
      "y": 7
    },
    {
      "x": 238,
      "y": 8
    },
    {
      "x": 238,
      "y": 9
    },
    {
      "x": 238,
      "y": 10
    },
    {
      "x": 238,
      "y": 11
    },
    {
      "x": 238,
      "y": 12
    },
    {
      "x": 238,
      "y": 13
    },
    {
      "x": 238,
      "y": 14
    },
    {
      "x": 238,
      "y": 15
    },
    {
      "x": 238,
      "y": 16
    },
    {
      "x": 238,
      "y": 17
    },
    {
      "x": 238,
      "y": 18
    },
    {
      "x": 238,
      "y": 19
    },
    {
      "x": 238,
      "y": 20
    },
    {
      "x": 238,
      "y": 21
    },
    {
      "x": 238,
      "y": 22
    },
    {
      "x": 238,
      "y": 23
    },
    {
      "x": 238,
      "y": 24
    },
    {
      "x": 238,
      "y": 25
    },
    {
      "x": 238,
      "y": 26
    },
    {
      "x": 238,
      "y": 27
    },
    {
      "x": 238,
      "y": 28
    },
    {
      "x": 238,
      "y": 29
    },
    {
      "x": 238,
      "y": 30
    },
    {
      "x": 238,
      "y": 31
    },
    {
      "x": 238,
      "y": 32
    },
    {
      "x": 239,
      "y": 9
    },
    {
      "x": 239,
      "y": 10
    },
    {
      "x": 239,
      "y": 11
    },
    {
      "x": 239,
      "y": 12
    },
    {
      "x": 239,
      "y": 13
    },
    {
      "x": 239,
      "y": 14
    },
    {
      "x": 239,
      "y": 15
    },
    {
      "x": 239,
      "y": 16
    },
    {
      "x": 239,
      "y": 17
    },
    {
      "x": 239,
      "y": 18
    },
    {
      "x": 239,
      "y": 19
    },
    {
      "x": 239,
      "y": 20
    },
    {
      "x": 239,
      "y": 21
    },
    {
      "x": 239,
      "y": 22
    },
    {
      "x": 239,
      "y": 23
    },
    {
      "x": 239,
      "y": 24
    },
    {
      "x": 239,
      "y": 25
    },
    {
      "x": 239,
      "y": 26
    },
    {
      "x": 239,
      "y": 27
    },
    {
      "x": 239,
      "y": 28
    },
    {
      "x": 240,
      "y": 16
    },
    {
      "x": 240,
      "y": 17
    },
    {
      "x": 240,
      "y": 18
    },
    {
      "x": 240,
      "y": 19
    },
    {
      "x": 240,
      "y": 20
    },
    {
      "x": 240,
      "y": 21
    },
    {
      "x": 241,
      "y": 16
    },
    {
      "x": 241,
      "y": 17
    },
    {
      "x": 241,
      "y": 18
    },
    {
      "x": 241,
      "y": 19
    },
    {
      "x": 241,
      "y": 20
    },
    {
      "x": 241,
      "y": 21
    },
    {
      "x": 242,
      "y": 17
    },
    {
      "x": 242,
      "y": 18
    },
    {
      "x": 242,
      "y": 19
    },
    {
      "x": 242,
      "y": 20
    },
    {
      "x": 243,
      "y": 15
    },
    {
      "x": 243,
      "y": 16
    },
    {
      "x": 243,
      "y": 17
    },
    {
      "x": 243,
      "y": 18
    },
    {
      "x": 243,
      "y": 19
    },
    {
      "x": 243,
      "y": 20
    },
    {
      "x": 243,
      "y": 21
    },
    {
      "x": 244,
      "y": 14
    },
    {
      "x": 244,
      "y": 15
    },
    {
      "x": 244,
      "y": 16
    },
    {
      "x": 244,
      "y": 17
    },
    {
      "x": 244,
      "y": 18
    },
    {
      "x": 244,
      "y": 19
    },
    {
      "x": 244,
      "y": 20
    },
    {
      "x": 244,
      "y": 21
    },
    {
      "x": 244,
      "y": 22
    },
    {
      "x": 245,
      "y": 15
    },
    {
      "x": 245,
      "y": 16
    },
    {
      "x": 245,
      "y": 17
    },
    {
      "x": 245,
      "y": 18
    },
    {
      "x": 245,
      "y": 19
    },
    {
      "x": 245,
      "y": 20
    },
    {
      "x": 245,
      "y": 21
    }
  ]
}